[
 {
  "organismo_nombre":"Hospital Regional de Rancagua",
  "base":"Contrata",
  "Enero_2024":3300,
  "Febrero_2024":3389,
  "Marzo_2024":3419,
  "Abril_2024":3261,
  "Mayo_2024":3210,
  "Junio_2024":3168,
  "Julio_2024":0,
  "Agosto_2024":3230,
  "Septiembre_2024":3185,
  "Octubre_2024":3472,
  "Noviembre_2024":3473,
  "Diciembre_2024":3488,
  "Enero_2025":3493,
  "Febrero_2025":3604,
  "Marzo_2025":3597,
  "Abril_2025":3439,
  "Mayo_2025":3470,
  "Junio_2025":3394
 },
 {
  "organismo_nombre":"Hospital Regional de Rancagua",
  "base":"Honorarios",
  "Enero_2024":17,
  "Febrero_2024":18,
  "Marzo_2024":18,
  "Abril_2024":16,
  "Mayo_2024":37,
  "Junio_2024":118,
  "Julio_2024":148,
  "Agosto_2024":147,
  "Septiembre_2024":113,
  "Octubre_2024":84,
  "Noviembre_2024":45,
  "Diciembre_2024":70,
  "Enero_2025":14,
  "Febrero_2025":12,
  "Marzo_2025":5,
  "Abril_2025":19,
  "Mayo_2025":30,
  "Junio_2025":76
 },
 {
  "organismo_nombre":"Hospital Regional de Rancagua",
  "base":"Planta",
  "Enero_2024":929,
  "Febrero_2024":908,
  "Marzo_2024":906,
  "Abril_2024":979,
  "Mayo_2024":981,
  "Junio_2024":988,
  "Julio_2024":1012,
  "Agosto_2024":985,
  "Septiembre_2024":1034,
  "Octubre_2024":758,
  "Noviembre_2024":755,
  "Diciembre_2024":0,
  "Enero_2025":756,
  "Febrero_2025":757,
  "Marzo_2025":757,
  "Abril_2025":740,
  "Mayo_2025":738,
  "Junio_2025":737
 }
]