[
 {
  "organismo_nombre":"CFT de la Región de la Araucanía",
  "base":"Cod. Trabajo",
  "Enero_2024":52,
  "Febrero_2024":55,
  "Marzo_2024":68,
  "Abril_2024":69,
  "Mayo_2024":71,
  "Junio_2024":79,
  "Julio_2024":80,
  "Agosto_2024":85,
  "Septiembre_2024":85,
  "Octubre_2024":88,
  "Noviembre_2024":95,
  "Diciembre_2024":96,
  "Enero_2025":94,
  "Febrero_2025":92,
  "Marzo_2025":89,
  "Abril_2025":93,
  "Mayo_2025":93,
  "Junio_2025":92
 },
 {
  "organismo_nombre":"CFT de la Región de la Araucanía",
  "base":"Honorarios",
  "Enero_2024":18,
  "Febrero_2024":5,
  "Marzo_2024":14,
  "Abril_2024":13,
  "Mayo_2024":120,
  "Junio_2024":113,
  "Julio_2024":118,
  "Agosto_2024":115,
  "Septiembre_2024":111,
  "Octubre_2024":117,
  "Noviembre_2024":110,
  "Diciembre_2024":130,
  "Enero_2025":11,
  "Febrero_2025":9,
  "Marzo_2025":6,
  "Abril_2025":9,
  "Mayo_2025":132,
  "Junio_2025":131
 }
]