[
 {
  "organismo_nombre":"Municipalidad de Chépica",
  "base":"Cod. Trabajo",
  "Enero_2024":298,
  "Febrero_2024":273,
  "Marzo_2024":274,
  "Abril_2024":276,
  "Mayo_2024":278,
  "Junio_2024":272,
  "Julio_2024":271,
  "Agosto_2024":272,
  "Septiembre_2024":271,
  "Octubre_2024":264,
  "Noviembre_2024":263,
  "Diciembre_2024":261,
  "Enero_2025":265,
  "Febrero_2025":254,
  "Marzo_2025":256,
  "Abril_2025":261,
  "Mayo_2025":261,
  "Junio_2025":261
 },
 {
  "organismo_nombre":"Municipalidad de Chépica",
  "base":"Contrata",
  "Enero_2024":143,
  "Febrero_2024":145,
  "Marzo_2024":152,
  "Abril_2024":154,
  "Mayo_2024":155,
  "Junio_2024":153,
  "Julio_2024":157,
  "Agosto_2024":155,
  "Septiembre_2024":156,
  "Octubre_2024":158,
  "Noviembre_2024":158,
  "Diciembre_2024":156,
  "Enero_2025":159,
  "Febrero_2025":155,
  "Marzo_2025":150,
  "Abril_2025":151,
  "Mayo_2025":147,
  "Junio_2025":144
 },
 {
  "organismo_nombre":"Municipalidad de Chépica",
  "base":"Honorarios",
  "Enero_2024":135,
  "Febrero_2024":134,
  "Marzo_2024":143,
  "Abril_2024":148,
  "Mayo_2024":163,
  "Junio_2024":168,
  "Julio_2024":178,
  "Agosto_2024":172,
  "Septiembre_2024":167,
  "Octubre_2024":172,
  "Noviembre_2024":170,
  "Diciembre_2024":172,
  "Enero_2025":133,
  "Febrero_2025":143,
  "Marzo_2025":150,
  "Abril_2025":150,
  "Mayo_2025":170,
  "Junio_2025":182
 },
 {
  "organismo_nombre":"Municipalidad de Chépica",
  "base":"Planta",
  "Enero_2024":271,
  "Febrero_2024":271,
  "Marzo_2024":271,
  "Abril_2024":264,
  "Mayo_2024":264,
  "Junio_2024":263,
  "Julio_2024":264,
  "Agosto_2024":264,
  "Septiembre_2024":265,
  "Octubre_2024":265,
  "Noviembre_2024":265,
  "Diciembre_2024":264,
  "Enero_2025":265,
  "Febrero_2025":264,
  "Marzo_2025":263,
  "Abril_2025":262,
  "Mayo_2025":264,
  "Junio_2025":262
 }
]