[
 {
  "organismo_nombre":"Municipalidad de Chill치n Viejo",
  "base":"Cod. Trabajo",
  "Enero_2024":199,
  "Febrero_2024":224,
  "Marzo_2024":203,
  "Abril_2024":214,
  "Mayo_2024":0,
  "Junio_2024":215,
  "Julio_2024":219,
  "Agosto_2024":220,
  "Septiembre_2024":220,
  "Octubre_2024":224,
  "Noviembre_2024":223,
  "Diciembre_2024":3,
  "Enero_2025":206,
  "Febrero_2025":3,
  "Marzo_2025":2,
  "Abril_2025":3,
  "Mayo_2025":2,
  "Junio_2025":3
 },
 {
  "organismo_nombre":"Municipalidad de Chill치n Viejo",
  "base":"Contrata",
  "Enero_2024":173,
  "Febrero_2024":165,
  "Marzo_2024":165,
  "Abril_2024":159,
  "Mayo_2024":163,
  "Junio_2024":161,
  "Julio_2024":154,
  "Agosto_2024":159,
  "Septiembre_2024":158,
  "Octubre_2024":156,
  "Noviembre_2024":212,
  "Diciembre_2024":226,
  "Enero_2025":229,
  "Febrero_2025":162,
  "Marzo_2025":160,
  "Abril_2025":166,
  "Mayo_2025":161,
  "Junio_2025":162
 },
 {
  "organismo_nombre":"Municipalidad de Chill치n Viejo",
  "base":"Honorarios",
  "Enero_2024":169,
  "Febrero_2024":180,
  "Marzo_2024":184,
  "Abril_2024":188,
  "Mayo_2024":189,
  "Junio_2024":196,
  "Julio_2024":201,
  "Agosto_2024":206,
  "Septiembre_2024":199,
  "Octubre_2024":230,
  "Noviembre_2024":335,
  "Diciembre_2024":340,
  "Enero_2025":260,
  "Febrero_2025":257,
  "Marzo_2025":249,
  "Abril_2025":286,
  "Mayo_2025":306,
  "Junio_2025":286
 },
 {
  "organismo_nombre":"Municipalidad de Chill치n Viejo",
  "base":"Planta",
  "Enero_2024":263,
  "Febrero_2024":263,
  "Marzo_2024":268,
  "Abril_2024":268,
  "Mayo_2024":267,
  "Junio_2024":268,
  "Julio_2024":268,
  "Agosto_2024":268,
  "Septiembre_2024":268,
  "Octubre_2024":268,
  "Noviembre_2024":308,
  "Diciembre_2024":308,
  "Enero_2025":305,
  "Febrero_2025":204,
  "Marzo_2025":204,
  "Abril_2025":202,
  "Mayo_2025":201,
  "Junio_2025":202
 }
]