[
 {
  "organismo_nombre":"Municipalidad de Futrono",
  "base":"Cod. Trabajo",
  "Enero_2024":239,
  "Febrero_2024":236,
  "Marzo_2024":234,
  "Abril_2024":222,
  "Mayo_2024":223,
  "Junio_2024":229,
  "Julio_2024":222,
  "Agosto_2024":233,
  "Septiembre_2024":228,
  "Octubre_2024":227,
  "Noviembre_2024":230,
  "Diciembre_2024":252,
  "Enero_2025":255,
  "Febrero_2025":241,
  "Marzo_2025":238,
  "Abril_2025":219,
  "Mayo_2025":231,
  "Junio_2025":224
 },
 {
  "organismo_nombre":"Municipalidad de Futrono",
  "base":"Contrata",
  "Enero_2024":154,
  "Febrero_2024":153,
  "Marzo_2024":142,
  "Abril_2024":139,
  "Mayo_2024":147,
  "Junio_2024":150,
  "Julio_2024":154,
  "Agosto_2024":151,
  "Septiembre_2024":155,
  "Octubre_2024":149,
  "Noviembre_2024":155,
  "Diciembre_2024":156,
  "Enero_2025":165,
  "Febrero_2025":175,
  "Marzo_2025":163,
  "Abril_2025":162,
  "Mayo_2025":159,
  "Junio_2025":165
 },
 {
  "organismo_nombre":"Municipalidad de Futrono",
  "base":"Honorarios",
  "Enero_2024":127,
  "Febrero_2024":207,
  "Marzo_2024":212,
  "Abril_2024":217,
  "Mayo_2024":210,
  "Junio_2024":216,
  "Julio_2024":199,
  "Agosto_2024":214,
  "Septiembre_2024":212,
  "Octubre_2024":220,
  "Noviembre_2024":237,
  "Diciembre_2024":244,
  "Enero_2025":145,
  "Febrero_2025":204,
  "Marzo_2025":204,
  "Abril_2025":236,
  "Mayo_2025":245,
  "Junio_2025":246
 },
 {
  "organismo_nombre":"Municipalidad de Futrono",
  "base":"Planta",
  "Enero_2024":305,
  "Febrero_2024":304,
  "Marzo_2024":301,
  "Abril_2024":301,
  "Mayo_2024":301,
  "Junio_2024":302,
  "Julio_2024":302,
  "Agosto_2024":301,
  "Septiembre_2024":301,
  "Octubre_2024":302,
  "Noviembre_2024":302,
  "Diciembre_2024":306,
  "Enero_2025":301,
  "Febrero_2025":300,
  "Marzo_2025":298,
  "Abril_2025":299,
  "Mayo_2025":298,
  "Junio_2025":299
 }
]