[
 {
  "organismo_nombre":"Municipalidad de Purranque",
  "base":"Cod. Trabajo",
  "Enero_2024":112,
  "Febrero_2024":114,
  "Marzo_2024":111,
  "Abril_2024":114,
  "Mayo_2024":116,
  "Junio_2024":117,
  "Julio_2024":114,
  "Agosto_2024":116,
  "Septiembre_2024":117,
  "Octubre_2024":116,
  "Noviembre_2024":116,
  "Diciembre_2024":113,
  "Enero_2025":82,
  "Febrero_2025":112,
  "Marzo_2025":114,
  "Abril_2025":114,
  "Mayo_2025":110,
  "Junio_2025":111
 },
 {
  "organismo_nombre":"Municipalidad de Purranque",
  "base":"Contrata",
  "Enero_2024":159,
  "Febrero_2024":157,
  "Marzo_2024":161,
  "Abril_2024":172,
  "Mayo_2024":176,
  "Junio_2024":181,
  "Julio_2024":181,
  "Agosto_2024":187,
  "Septiembre_2024":186,
  "Octubre_2024":186,
  "Noviembre_2024":178,
  "Diciembre_2024":185,
  "Enero_2025":188,
  "Febrero_2025":191,
  "Marzo_2025":194,
  "Abril_2025":194,
  "Mayo_2025":201,
  "Junio_2025":203
 },
 {
  "organismo_nombre":"Municipalidad de Purranque",
  "base":"Honorarios",
  "Enero_2024":107,
  "Febrero_2024":98,
  "Marzo_2024":95,
  "Abril_2024":90,
  "Mayo_2024":92,
  "Junio_2024":111,
  "Julio_2024":113,
  "Agosto_2024":121,
  "Septiembre_2024":124,
  "Octubre_2024":114,
  "Noviembre_2024":118,
  "Diciembre_2024":115,
  "Enero_2025":77,
  "Febrero_2025":75,
  "Marzo_2025":86,
  "Abril_2025":89,
  "Mayo_2025":89,
  "Junio_2025":92
 },
 {
  "organismo_nombre":"Municipalidad de Purranque",
  "base":"Planta",
  "Enero_2024":350,
  "Febrero_2024":348,
  "Marzo_2024":348,
  "Abril_2024":342,
  "Mayo_2024":339,
  "Junio_2024":342,
  "Julio_2024":341,
  "Agosto_2024":340,
  "Septiembre_2024":339,
  "Octubre_2024":338,
  "Noviembre_2024":338,
  "Diciembre_2024":345,
  "Enero_2025":341,
  "Febrero_2025":338,
  "Marzo_2025":334,
  "Abril_2025":335,
  "Mayo_2025":331,
  "Junio_2025":332
 }
]